d3_tb_agent_comms/__init__.py
d3_tb_agent_comms/custom_types.py
d3_tb_agent_comms/main.py
d3_tb_agent_comms/py.typed
d3_tb_agent_comms-0.2.10.dist-info/WHEEL
d3_tb_agent_comms-0.2.10.dist-info/METADATA
d3_tb_agent_comms-0.2.10.dist-info/RECORD
