Metadata-Version: 2.3
Name: d3-tb-agent-comms
Version: 0.2.10
Summary: Lib that holds a Class for easily interacting with TB-Agent Endpoints
Author: Oscar Mitchell
Author-email: Oscar Mitchell <oscar.mitchell@disguise.one>
Requires-Dist: requests>=2.32.5
Requires-Python: >=3.12
